collective.portlet.embed-2.0.0-py3.13-nspkg.pth
collective/portlet/embed/__init__.py
collective/portlet/embed/configure.zcml
collective/portlet/embed/portlet.pt
collective/portlet/embed/portlet.py
collective/portlet/embed/rebuild_i18n.sh
collective/portlet/embed/testing.py
collective/portlet/embed/locales/collective.portlet.embed-manual.pot
collective/portlet/embed/locales/collective.portlet.embed.pot
collective/portlet/embed/locales/en/LC_MESSAGES/collective.portlet.embed.po
collective/portlet/embed/locales/fr/LC_MESSAGES/collective.portlet.embed.po
collective/portlet/embed/locales/it/LC_MESSAGES/collective.portlet.embed.po
collective/portlet/embed/locales/nl/LC_MESSAGES/collective.portlet.embed.po
collective/portlet/embed/profiles/default/metadata.xml
collective/portlet/embed/profiles/default/portlets.xml
collective/portlet/embed/tests/__init__.py
collective/portlet/embed/tests/base.py
collective/portlet/embed/tests/test_portlet.py
collective/portlet/embed/tests/test_robot.py
collective/portlet/embed/tests/test_robot.robot
collective_portlet_embed-2.0.0.dist-info/METADATA
collective_portlet_embed-2.0.0.dist-info/WHEEL
collective_portlet_embed-2.0.0.dist-info/entry_points.txt
collective_portlet_embed-2.0.0.dist-info/namespace_packages.txt
collective_portlet_embed-2.0.0.dist-info/top_level.txt
collective_portlet_embed-2.0.0.dist-info/RECORD
