Metadata-Version: 2.4
Name: collective.portlet.embed
Version: 2.0.0
Summary: Embed an HTML snippet in a Plone portlet
Home-page: https://github.com/collective/collective.portlet.embed
Author: JeanMichel FRANCOIS aka toutpt
Author-email: toutpt@gmail.com
Maintainer: keul
Maintainer-email: luca@keul.it
License: GPL
Keywords: plone portlet embed iframe
Classifier: Environment :: Web Environment
Classifier: License :: OSI Approved :: GNU General Public License (GPL)
Classifier: Operating System :: OS Independent
Classifier: Framework :: Plone
Classifier: Framework :: Plone :: 5.2
Classifier: Framework :: Plone :: 6.0
Classifier: Framework :: Plone :: 6.1
Classifier: Programming Language :: Python
Requires-Dist: setuptools
Requires-Dist: Products.CMFPlone>=4.0
Requires-Dist: z3c.form
Provides-Extra: test
Requires-Dist: plone.app.testing; extra == "test"
Requires-Dist: plone.app.robotframework; extra == "test"
Requires-Dist: selenium; extra == "test"
Dynamic: author
Dynamic: author-email
Dynamic: classifier
Dynamic: description
Dynamic: home-page
Dynamic: keywords
Dynamic: license
Dynamic: maintainer
Dynamic: maintainer-email
Dynamic: provides-extra
Dynamic: requires-dist
Dynamic: summary
